setup.cfg
setup.py
github_email/__init__.py
github_email/main.py
github_email.egg-info/PKG-INFO
github_email.egg-info/SOURCES.txt
github_email.egg-info/dependency_links.txt
github_email.egg-info/requires.txt
github_email.egg-info/top_level.txt