Metadata-Version: 1.1
Name: github-email
Version: 0.0.4
Summary: Get email ID of any GitHub user
Home-page: https://github.com/prabhakar267/github_email
Author: Prabhakar Gupta
Author-email: prabhakargupta267@gmail.com
License: MIT
Download-URL: https://github.com/prabhakar267/github_email/tarball/0.0.4
Keywords: github,email,user,public,commit,get
Platform: UNKNOWN
